odoo/addons/impersonate_login/README.rst
odoo/addons/impersonate_login/__init__.py
odoo/addons/impersonate_login/__manifest__.py
odoo/addons/impersonate_login/hooks.py
odoo/addons/impersonate_login/i18n/impersonate_login.pot
odoo/addons/impersonate_login/i18n/it.po
odoo/addons/impersonate_login/models/__init__.py
odoo/addons/impersonate_login/models/impersonate_log.py
odoo/addons/impersonate_login/models/ir_http.py
odoo/addons/impersonate_login/models/mail_message.py
odoo/addons/impersonate_login/models/mail_thread.py
odoo/addons/impersonate_login/models/model.py
odoo/addons/impersonate_login/models/res_config_settings.py
odoo/addons/impersonate_login/models/res_users.py
odoo/addons/impersonate_login/readme/CONTRIBUTORS.rst
odoo/addons/impersonate_login/readme/DESCRIPTION.rst
odoo/addons/impersonate_login/readme/USAGE.rst
odoo/addons/impersonate_login/security/group.xml
odoo/addons/impersonate_login/security/ir.model.access.csv
odoo/addons/impersonate_login/static/description/icon.png
odoo/addons/impersonate_login/static/description/index.html
odoo/addons/impersonate_login/static/src/css/navbar.scss
odoo/addons/impersonate_login/static/src/js/abstract_web_client.js
odoo/addons/impersonate_login/static/src/js/user_menu.js
odoo/addons/impersonate_login/static/src/xml/user_menu.xml
odoo/addons/impersonate_login/tests/__init__.py
odoo/addons/impersonate_login/tests/test_impersonate_login.py
odoo/addons/impersonate_login/views/assets.xml
odoo/addons/impersonate_login/views/impersonate_log.xml
odoo/addons/impersonate_login/views/res_config_settings.xml
odoo/addons/impersonate_login/views/res_users.xml
odoo14_addon_impersonate_login-14.0.1.0.1.dist-info/METADATA
odoo14_addon_impersonate_login-14.0.1.0.1.dist-info/WHEEL
odoo14_addon_impersonate_login-14.0.1.0.1.dist-info/top_level.txt
odoo14_addon_impersonate_login-14.0.1.0.1.dist-info/RECORD
